lib2fas/__about__.py
lib2fas/__init__.py
lib2fas/_security.py
lib2fas/_types.py
lib2fas/core.py
lib2fas/py.typed
lib2fas/utils.py
lib2fas-0.1.10.dist-info/METADATA
lib2fas-0.1.10.dist-info/WHEEL
lib2fas-0.1.10.dist-info/licenses/LICENSE
lib2fas-0.1.10.dist-info/RECORD
