Metadata-Version: 2.4
Name: lib2fas
Version: 0.1.10
Summary: Unofficial implementation of 2fas for Python (as a library)
Project-URL: Documentation, https://github.com/robinvandernoord/lib2fas-python#readme
Project-URL: Issues, https://github.com/robinvandernoord/lib2fas-python/issues
Project-URL: Source, https://github.com/robinvandernoord/lib2fas-python
Author-email: Robin van der Noord <robinvandernoord@gmail.com>
License-Expression: MIT
License-File: LICENSE
Classifier: Development Status :: 4 - Beta
Classifier: Programming Language :: Python
Classifier: Programming Language :: Python :: 3.11
Classifier: Programming Language :: Python :: 3.12
Classifier: Programming Language :: Python :: 3.13
Classifier: Programming Language :: Python :: 3.14
Classifier: Programming Language :: Python :: Implementation :: CPython
Classifier: Programming Language :: Python :: Implementation :: PyPy
Requires-Python: >=3.11
Requires-Dist: configuraptor>=1.26.1
Requires-Dist: cryptography
Requires-Dist: keyring
Requires-Dist: pyjson5
Requires-Dist: pyotp
Requires-Dist: rapidfuzz
Provides-Extra: dev
Requires-Dist: edwh; extra == 'dev'
Requires-Dist: hatch; extra == 'dev'
Requires-Dist: pytest-mypy-testing; extra == 'dev'
Requires-Dist: python-semantic-release<8; extra == 'dev'
Requires-Dist: su6[all]; extra == 'dev'
